LICENSE
MANIFEST.in
README.md
VERSION
setup.cfg
setup.py
sqlalchemy_gql/__init__.py
sqlalchemy_gql/context.py
sqlalchemy_gql/mapper.py
sqlalchemy_gql/mixin.py
sqlalchemy_gql/orm_base.py
sqlalchemy_gql/relay_base.py
sqlalchemy_gql.egg-info/PKG-INFO
sqlalchemy_gql.egg-info/SOURCES.txt
sqlalchemy_gql.egg-info/dependency_links.txt
sqlalchemy_gql.egg-info/requires.txt
sqlalchemy_gql.egg-info/top_level.txt
tests/__init__.py
tests/test_base.py
tests/test_context.py
tests/test_db_manager.py
tests/test_relay_base.py
tests/test_sqlalachemy_orm.py
tests/test_sqlmodel.py