Metadata-Version: 2.1
Name: sqlalchemy-gql
Version: 1.3.14
Summary: Map SQLAlchemy models to GraphQL Objects.
Home-page: https://gitlab.com/parob/sqlalchemy-gql
Download-URL: https://gitlab.com/parob/sqlalchemy-gql/-/archive/v1.3.14/sqlalchemy-gql-v1.3.14.tar.gz
Author: Robert Parker
Author-email: rob@parob.com
License: MIT
Keywords: GraphQL,GraphQL API,Server,DataRM,ORM
Classifier: Development Status :: 3 - Alpha
Classifier: Intended Audience :: Developers
Classifier: Programming Language :: Python :: 3
Classifier: License :: OSI Approved :: MIT License
Classifier: Operating System :: OS Independent
License-File: LICENSE
